ezregex/EZRegex.py
ezregex/EZRegex.pyi
ezregex/__init__.py
ezregex/_docs.py
ezregex/api.py
ezregex/api.pyi
ezregex/generate.py
ezregex/invert.py
ezregex/invert_old.py
ezregex/PCRE2/PCRE2EZRegex.py
ezregex/PCRE2/__init__.py
ezregex/PCRE2/elements.py
ezregex/PCRE2/elements.pyi
ezregex/R/REZRegex.py
ezregex/R/__init__.py
ezregex/R/elements.py
ezregex/R/elements.pyi
ezregex/assets/common_sorted_words.json
ezregex/assets/sorted_words.json
ezregex/base/__init__.py
ezregex/base/elements.py
ezregex/base/interface.py
ezregex/javascript/JavaScriptEZRegex.py
ezregex/javascript/__init__.py
ezregex/javascript/elements.py
ezregex/javascript/elements.pyi
ezregex/python/PythonEZRegex.py
ezregex/python/PythonEZRegex.pyi
ezregex/python/__init__.py
ezregex/python/elements.py
ezregex/python/elements.pyi
ezregex-2.4.0.dist-info/METADATA
ezregex-2.4.0.dist-info/WHEEL
ezregex-2.4.0.dist-info/licenses/LICENSE
ezregex-2.4.0.dist-info/RECORD
