Metadata-Version: 2.4
Name: ezregex
Version: 2.4.0
Summary: A readable and intuitive way to generate Regular Expressions
Project-URL: Documentation, https://github.com/smartycope/ezregex?tab=readme-ov-file#documentation
Project-URL: Issues, https://github.com/smartycope/ezregex/issues
Project-URL: Source, https://github.com/smartycope/ezregex
Project-URL: Official Website, https://ezregex.org
Author-email: Copeland Carter <smartycope@gmail.com>
License-Expression: MIT
License-File: LICENSE
Classifier: Development Status :: 4 - Beta
Classifier: Programming Language :: Python
Classifier: Programming Language :: Python :: 3.10
Classifier: Programming Language :: Python :: 3.11
Classifier: Programming Language :: Python :: 3.12
Classifier: Programming Language :: Python :: Implementation :: CPython
Classifier: Programming Language :: Python :: Implementation :: PyPy
Requires-Python: >=3.10
